.gitignore
.travis.yml
LICENSE.txt
LICENSE_Apache.txt
MANIFEST.in
Makefile
README.rst
dev_requirements.txt
re6ference-one
re6ference-sloppy-one
reference-one
reference-sloppy-one
setup.cfg
setup.py
tox.ini
docs/Makefile
docs/source/conf.py
docs/source/converter-tests.rst
docs/source/index.rst
docs/source/iptables-converter.rst
docs/source/sources.rst
iptables_conv/__init__.py
iptables_conv/iptables_converter.py
iptables_converter.egg-info/PKG-INFO
iptables_converter.egg-info/SOURCES.txt
iptables_converter.egg-info/dependency_links.txt
iptables_converter.egg-info/entry_points.txt
iptables_converter.egg-info/top_level.txt
man/ip6tables-converter.8
man/iptables-converter.8
tests/__init__.py
tests/test_iptables_converter.py
tests/test_iptables_options.py
tests/data/test-debian-bug-no-748638
tests/data/test-shell-variables