Metadata-Version: 1.1
Name: iptables-converter
Version: 0.9.10
Summary: convert set of iptables-commands to iptables-save format
Home-page: https://github.com/sl0/conv.git
Author: Johannes Hubertz
Author-email: johannes@hubertz.de
License: GNU General Public License version 3 or later, Apache License Version 2
Platform: Linux
Classifier: Development Status :: 5 - Production/Stable
Classifier: License :: OSI Approved :: GNU General Public License v3 or later (GPLv3+)
Classifier: License :: OSI Approved :: Apache Software License
Classifier: Intended Audience :: System Administrators
Classifier: Operating System :: POSIX :: Linux
Classifier: Programming Language :: Python :: 2.7
Classifier: Programming Language :: Python :: 3
Classifier: Topic :: Security
Classifier: Topic :: System :: Networking :: Firewalls
Classifier: Topic :: Utilities
